fastai-splunk/__init__.py
fastai-splunk/data.py
fastai-splunk/learner.py
fastai-splunk/models.py
fastai-splunk/transform.py
fastai_splunk/__init__.py
fastai_splunk/data.py
fastai_splunk/learner.py
fastai_splunk/models.py
fastai_splunk/transform.py
fastai_splunk-0.0.1.dist-info/LICENSE
fastai_splunk-0.0.1.dist-info/METADATA
fastai_splunk-0.0.1.dist-info/WHEEL
fastai_splunk-0.0.1.dist-info/top_level.txt
fastai_splunk-0.0.1.dist-info/RECORD
