Metadata-Version: 2.1
Name: fastai-splunk
Version: 0.0.1
Summary: fastai-splunk allows you to import Splunk data using fastai
Home-page: https://github.com/nargroves/fastai-splunk
Author: Nate Argroves
Author-email: nargroves@gmail.com
License: Apache Software License 2.0
Platform: UNKNOWN
Classifier: Development Status :: 4 - Beta
Classifier: Intended Audience :: Developers
Classifier: License :: OSI Approved :: Apache Software License
Classifier: Natural Language :: English
Classifier: Programming Language :: Python :: 3.6
Classifier: Programming Language :: Python :: 3.7
Requires-Python: >=3.6
Requires-Dist: fastai
Requires-Dist: splunk-sdk
